odoo/addons/product_sale_manufactured_for/README.rst
odoo/addons/product_sale_manufactured_for/__init__.py
odoo/addons/product_sale_manufactured_for/__manifest__.py
odoo/addons/product_sale_manufactured_for/i18n/es.po
odoo/addons/product_sale_manufactured_for/i18n/it.po
odoo/addons/product_sale_manufactured_for/i18n/product_sale_manufactured_for.pot
odoo/addons/product_sale_manufactured_for/migrations/14.0.1.1.0/post-migrate.py
odoo/addons/product_sale_manufactured_for/migrations/14.0.1.1.0/pre-migrate.py
odoo/addons/product_sale_manufactured_for/models/__init__.py
odoo/addons/product_sale_manufactured_for/models/product_product.py
odoo/addons/product_sale_manufactured_for/readme/CONTRIBUTORS.rst
odoo/addons/product_sale_manufactured_for/readme/CREDITS.rst
odoo/addons/product_sale_manufactured_for/readme/DESCRIPTION.rst
odoo/addons/product_sale_manufactured_for/static/description/icon.png
odoo/addons/product_sale_manufactured_for/static/description/index.html
odoo/addons/product_sale_manufactured_for/views/product_product.xml
odoo/addons/product_sale_manufactured_for/views/sale_order.xml
odoo14_addon_product_sale_manufactured_for-14.0.1.1.1.dev6.dist-info/METADATA
odoo14_addon_product_sale_manufactured_for-14.0.1.1.1.dev6.dist-info/WHEEL
odoo14_addon_product_sale_manufactured_for-14.0.1.1.1.dev6.dist-info/top_level.txt
odoo14_addon_product_sale_manufactured_for-14.0.1.1.1.dev6.dist-info/RECORD
